<annotation>
	<folder>Train</folder>
	<filename>C162.JPG</filename>
	<path>/root/Documents/Python_Chicken_Detect_Project/Train/C162.JPG</path>
	<source>
		<database>Unknown</database>
	</source>
	<size>
		<width>4000</width>
		<height>3000</height>
		<depth>3</depth>
	</size>
	<segmented>0</segmented>
	<object>
		<name>chicken</name>
		<pose>Unspecified</pose>
		<truncated>0</truncated>
		<difficult>0</difficult>
		<bndbox>
			<xmin>1442</xmin>
			<ymin>1465</ymin>
			<xmax>3057</xmax>
			<ymax>2649</ymax>
		</bndbox>
	</object>
	<object>
		<name>chicken</name>
		<pose>Unspecified</pose>
		<truncated>0</truncated>
		<difficult>0</difficult>
		<bndbox>
			<xmin>1657</xmin>
			<ymin>1096</ymin>
			<xmax>3007</xmax>
			<ymax>1699</ymax>
		</bndbox>
	</object>
	<object>
		<name>chicken</name>
		<pose>Unspecified</pose>
		<truncated>0</truncated>
		<difficult>0</difficult>
		<bndbox>
			<xmin>789</xmin>
			<ymin>1440</ymin>
			<xmax>1904</xmax>
			<ymax>2402</ymax>
		</bndbox>
	</object>
</annotation>
