<annotation>
	<folder>Train</folder>
	<filename>C189.JPG</filename>
	<path>/root/Documents/Python_Chicken_Detect_Project/Train/C189.JPG</path>
	<source>
		<database>Unknown</database>
	</source>
	<size>
		<width>4000</width>
		<height>3000</height>
		<depth>3</depth>
	</size>
	<segmented>0</segmented>
	<object>
		<name>chicken</name>
		<pose>Unspecified</pose>
		<truncated>1</truncated>
		<difficult>0</difficult>
		<bndbox>
			<xmin>420</xmin>
			<ymin>646</ymin>
			<xmax>2653</xmax>
			<ymax>3000</ymax>
		</bndbox>
	</object>
	<object>
		<name>chicken</name>
		<pose>Unspecified</pose>
		<truncated>0</truncated>
		<difficult>0</difficult>
		<bndbox>
			<xmin>992</xmin>
			<ymin>290</ymin>
			<xmax>2585</xmax>
			<ymax>1621</ymax>
		</bndbox>
	</object>
	<object>
		<name>chicken</name>
		<pose>Unspecified</pose>
		<truncated>0</truncated>
		<difficult>0</difficult>
		<bndbox>
			<xmin>3001</xmin>
			<ymin>546</ymin>
			<xmax>3751</xmax>
			<ymax>1196</ymax>
		</bndbox>
	</object>
</annotation>
